nameko_grpc_opentelemetry/__init__.py
nameko_grpc_opentelemetry/package.py
nameko_grpc_opentelemetry/tee.py
nameko_grpc_opentelemetry/version.py
opentelemetry_instrumentation_nameko_grpc-0.4.0.dist-info/LICENSE
opentelemetry_instrumentation_nameko_grpc-0.4.0.dist-info/METADATA
opentelemetry_instrumentation_nameko_grpc-0.4.0.dist-info/WHEEL
opentelemetry_instrumentation_nameko_grpc-0.4.0.dist-info/top_level.txt
opentelemetry_instrumentation_nameko_grpc-0.4.0.dist-info/zip-safe
opentelemetry_instrumentation_nameko_grpc-0.4.0.dist-info/RECORD
